{"001":{"name":"本店","kana":"ホンテン","hira":"ほんてん","roma":"honten"},"002":{"name":"富士見","kana":"フジミ","hira":"ふじみ","roma":"fujimi"},"004":{"name":"吉田","kana":"ヨシダ","hira":"よしだ","roma":"yoshida"},"005":{"name":"富戸","kana":"フト","hira":"ふと","roma":"futo"},"008":{"name":"伊東","kana":"イトウ","hira":"いとう","roma":"itou"},"009":{"name":"荻","kana":"オギ","hira":"おぎ","roma":"ogi"},"010":{"name":"伊豆高原","kana":"イズコウゲン","hira":"いずこうげん","roma":"izukougen"},"012":{"name":"静海","kana":"シズミ","hira":"しずみ","roma":"shizumi"},"020":{"name":"宇佐美","kana":"ウサミ","hira":"うさみ","roma":"usami"},"021":{"name":"下多賀","kana":"シモタガ","hira":"しもたが","roma":"shimotaga"},"024":{"name":"熱海","kana":"アタミ","hira":"あたみ","roma":"atami"},"025":{"name":"伊豆山","kana":"イズサン","hira":"いずさん","roma":"izusan"}}