{"001":{"name":"本所","kana":"ホンシヨ","hira":"ほんしよ","roma":"honshiyo"},"002":{"name":"浜田","kana":"ハマダ","hira":"はまだ","roma":"hamada"},"006":{"name":"浜田西","kana":"ハマダニシ","hira":"はまだにし","roma":"hamadanishi"},"009":{"name":"浜田東","kana":"ハマダヒガシ","hira":"はまだひがし","roma":"hamadahigashi"},"028":{"name":"江津","kana":"ゴウツ","hira":"ごうつ","roma":"goutsu"},"031":{"name":"江津西","kana":"ゴウツニシ","hira":"ごうつにし","roma":"goutsunishi"},"041":{"name":"三隅","kana":"ミスミ","hira":"みすみ","roma":"misumi"},"051":{"name":"雲城出張所","kana":"クモギ","hira":"くもぎ","roma":"kumogi"},"054":{"name":"金城","kana":"カナギ","hira":"かなぎ","roma":"kanagi"},"061":{"name":"弥栄","kana":"ヤサカ","hira":"やさか","roma":"yasaka"},"071":{"name":"旭","kana":"アサヒ","hira":"あさひ","roma":"asahi"}}